rep_grafos/__init__.py
rep_grafos/rep_graph_mod.py
rep_grafos/rep_graph_prob.py
rep_grafos/rep_graph_spatial_xor.py
rep_grafos/xor_descascavel_by_f.py
rep_grafos-0.2.3.dist-info/METADATA
rep_grafos-0.2.3.dist-info/WHEEL
rep_grafos-0.2.3.dist-info/top_level.txt
rep_grafos-0.2.3.dist-info/RECORD
