Metadata-Version: 2.4
Name: rep-grafos
Version: 0.2.3
Summary: Representações Monte Carlo, Las Vegas e Determinística de Grafos Massivos
Author-email: Paulo Leão <t5tt0yerl@mozmail.com>
License: MIT
Project-URL: Homepage, https://github.com/paulodiogo/rep-grafos
Project-URL: Repository, https://github.com/paulodiogo/rep-grafos
Requires-Python: >=3.8
Requires-Dist: mmh3
Requires-Dist: igraph
Provides-Extra: dev
Requires-Dist: pytest; extra == "dev"
